<?xml version="1.0" encoding="utf-8" ?>
<!-- Copyright 2019 Creu Blanca
     License AGPL-3.0 or later (http://www.gnu.org/licenses/agpl). -->
<odoo>
    <record model="ir.ui.view" id="hr_equipment_request_view_form_button_box">
        <field
            name="name"
        >maintenance.request.form (in maintenance_equipment_purchase)</field>
        <field name="model">maintenance.request</field>
        <field name="inherit_id" ref="base_maintenance.equipment_request_view_form" />
        <field name="groups_id" eval="[(4, ref('purchase.group_purchase_user'))]" />
        <field name="arch" type="xml">
            <notebook position="inside">
                <page name="purchase_order" string="Purchase Orders">
                    <field name="purchase_order_ids" />
                </page>
            </notebook>
        </field>
    </record>
</odoo>
